{
    "name": "flogo-javascript",
    "type": "flogo:activity",
    "ref": "github.com/kabukky/flogojs",
    "version": "0.0.1",
    "title": "JavaScript Activity Kabukky",
    "description": "Run embedded JavaScript code",
    "homepage": "https://github.com/kabukky/flogojs",
    "inputs":[
      {
        "name": "jsInput",
        "type": "any"
      },
      {
        "name": "jsCode",
        "type": "string",
        "required": true
      }
    ],
    "outputs": [
      {
        "name": "jsOutput",
        "type": "any"
      }
    ]
  }
  